Metadata-Version: 2.1
Name: natali-cart-project
Version: 1.0
Summary: Корзина для магазину
Author: Natali
Author-email: tatiksunny1@gmail.com
